MANIFEST.in
setup.py
cmd/kickapp
kickapp/__init__.py
kickapp/info.py
kickapp/kickapp.py
kickapp/kickinit.py
kickapp/kicktools.py
kickapp.egg-info/PKG-INFO
kickapp.egg-info/SOURCES.txt
kickapp.egg-info/dependency_links.txt
kickapp.egg-info/top_level.txt
kickapp/djangoapps/__init__.py
kickapp/djangoapps/app/__init__.py
kickapp/djangoapps/app/admin.py
kickapp/djangoapps/app/apps.py
kickapp/djangoapps/app/models.py
kickapp/djangoapps/app/tests.py
kickapp/djangoapps/app/views.py
kickapp/djangoapps/app/migrations/__init__.py
kickapp/djangoapps/app/static/app/fonts/font-roboto/font-roboto.css
kickapp/djangoapps/app/static/app/fonts/font-roboto/roboto/Roboto-Black.ttf
kickapp/djangoapps/app/static/app/fonts/font-roboto/roboto/Roboto-BlackItalic.ttf
kickapp/djangoapps/app/static/app/fonts/font-roboto/roboto/Roboto-Bold.ttf
kickapp/djangoapps/app/static/app/fonts/font-roboto/roboto/Roboto-BoldItalic.ttf
kickapp/djangoapps/app/static/app/fonts/font-roboto/roboto/Roboto-Italic.ttf
kickapp/djangoapps/app/static/app/fonts/font-roboto/roboto/Roboto-Light.ttf
kickapp/djangoapps/app/static/app/fonts/font-roboto/roboto/Roboto-LightItalic.ttf
kickapp/djangoapps/app/static/app/fonts/font-roboto/roboto/Roboto-Medium.ttf
kickapp/djangoapps/app/static/app/fonts/font-roboto/roboto/Roboto-MediumItalic.ttf
kickapp/djangoapps/app/static/app/fonts/font-roboto/roboto/Roboto-Regular.ttf
kickapp/djangoapps/app/static/app/fonts/font-roboto/roboto/Roboto-Thin.ttf
kickapp/djangoapps/app/static/app/fonts/font-roboto/roboto/Roboto-ThinItalic.ttf
kickapp/djangoapps/app/static/app/fonts/font-roboto/roboto/RobotoCondensed-Bold.ttf
kickapp/djangoapps/app/static/app/fonts/font-roboto/roboto/RobotoCondensed-BoldItalic.ttf
kickapp/djangoapps/app/static/app/fonts/font-roboto/roboto/RobotoCondensed-Italic.ttf
kickapp/djangoapps/app/static/app/fonts/font-roboto/roboto/RobotoCondensed-Light.ttf
kickapp/djangoapps/app/static/app/fonts/font-roboto/roboto/RobotoCondensed-LightItalic.ttf
kickapp/djangoapps/app/static/app/fonts/font-roboto/roboto/RobotoCondensed-Regular.ttf
