Metadata-Version: 1.1
Name: kickapp
Version: 0.15
Summary: Deploy Django application on android as APK.
Home-page: http://yeisoncardona.com/
Author: Yeison Cardona
Author-email: yeisoneng@gmail.com
License: BSD License
Download-URL: https://bitbucket.org/yeisoneng/python-kickapp/downloads
Platform: UNKNOWN
Classifier: Environment :: Web Environment
Classifier: Framework :: Django
